README
setup.py
bambu_xmlrpc/__init__.py
bambu_xmlrpc/urls.py
bambu_xmlrpc/views.py
bambu_xmlrpc.egg-info/PKG-INFO
bambu_xmlrpc.egg-info/SOURCES.txt
bambu_xmlrpc.egg-info/dependency_links.txt
bambu_xmlrpc.egg-info/requires.txt
bambu_xmlrpc.egg-info/top_level.txt