Metadata-Version: 1.1
Name: bambu-xmlrpc
Version: 2.0
Summary: An extensible XML-RPC provider
Home-page: https://github.com/iamsteadman/bambu-xmlrpc
Author: Steadman
Author-email: mark@steadman.io
License: UNKNOWN
Platform: UNKNOWN
Classifier: Development Status :: 4 - Beta
Classifier: Environment :: Web Environment
Classifier: Framework :: Django
